tkinterweb/__init__.py
tkinterweb/bindings.py
tkinterweb/dom.py
tkinterweb/extensions.py
tkinterweb/handlers.py
tkinterweb/htmlwidgets.py
tkinterweb/imageutils.py
tkinterweb/js.py
tkinterweb/subwidgets.py
tkinterweb/utilities.py
tkinterweb/resources/combobox-2.3.tm
tkinterweb/resources/pkgIndex.tcl
tkinterweb-4.17.6.dist-info/LICENSE.md
tkinterweb-4.17.6.dist-info/METADATA
tkinterweb-4.17.6.dist-info/WHEEL
tkinterweb-4.17.6.dist-info/top_level.txt
tkinterweb-4.17.6.dist-info/RECORD
