Metadata-Version: 2.1
Name: tkinterweb
Version: 4.17.6
Summary: HTML/CSS viewer, editor, and app builder for Tkinter
Home-page: https://github.com/Andereoo/TkinterWeb
License: MIT
Keywords: tkinter,Tkinter,tkhtml,Tkhtml,Tk,HTML,CSS,webbrowser
Classifier: Intended Audience :: Developers
Classifier: License :: Freeware
Classifier: License :: OSI Approved :: MIT License
Classifier: Natural Language :: English
Classifier: Programming Language :: Python
Classifier: Programming Language :: Python :: 3
Classifier: Topic :: Software Development
Requires-Python: >=3.2
License-File: LICENSE.md
Requires-Dist: tkinterweb-tkhtml >=2.1.0
Provides-Extra: full
Requires-Dist: brotli ; extra == 'full'
Requires-Dist: cairosvg ; extra == 'full'
Requires-Dist: pillow ; extra == 'full'
Requires-Dist: pythonmonkey ; extra == 'full'
Requires-Dist: tkinterweb-tkhtml-extras >=1.2.0 ; extra == 'full'
Provides-Extra: html
Requires-Dist: tkinterweb-tkhtml-extras >=1.2.0 ; extra == 'html'
Provides-Extra: images
Requires-Dist: pillow ; extra == 'images'
Provides-Extra: javascript
Requires-Dist: pythonmonkey ; extra == 'javascript'
Provides-Extra: recommended
Requires-Dist: pillow ; extra == 'recommended'
Requires-Dist: tkinterweb-tkhtml-extras >=1.2.0 ; extra == 'recommended'
Provides-Extra: requests
Requires-Dist: brotli ; extra == 'requests'
Provides-Extra: svg
Requires-Dist: cairosvg ; extra == 'svg'
Requires-Dist: pillow ; extra == 'svg'
Requires-Dist: tkinterweb-tkhtml-extras >=1.2.0 ; extra == 'svg'
